pyapns_client/__init__.py
pyapns_client/async_client.py
pyapns_client/auth.py
pyapns_client/base.py
pyapns_client/client.py
pyapns_client/exceptions.py
pyapns_client/logging.py
pyapns_client/notification.py
pyapns_client3-3.0.6.dist-info/LICENSE.rst
pyapns_client3-3.0.6.dist-info/METADATA
pyapns_client3-3.0.6.dist-info/WHEEL
pyapns_client3-3.0.6.dist-info/top_level.txt
pyapns_client3-3.0.6.dist-info/RECORD
