Metadata-Version: 2.1
Name: pyapns-client3
Version: 3.0.6
Summary: Simple, flexible and fast Apple Push Notifications on iOS, OSX and Safari using the HTTP/2 Push provider API with async support.
Home-page: https://github.com/capcom6/pyapns_client
Author: Jakub Kleň
Author-email: kukosk@gmail.com
Maintainer: Aleksandr Soloshenko
Maintainer-email: capcom2me@gmail.com
License: MIT License
Keywords: apns apple ios osx safari push notifications
Platform: any
Classifier: Development Status :: 5 - Production/Stable
Classifier: Intended Audience :: Developers
Classifier: Operating System :: OS Independent
Classifier: License :: OSI Approved :: MIT License
Classifier: Topic :: Communications
Classifier: Topic :: Internet
Classifier: Topic :: Software Development :: Libraries :: Python Modules
Classifier: Topic :: Utilities
Classifier: Programming Language :: Python
Classifier: Programming Language :: Python :: 3
Classifier: Programming Language :: Python :: 3.6
Classifier: Programming Language :: Python :: 3.7
Classifier: Programming Language :: Python :: 3.8
Classifier: Programming Language :: Python :: 3.9
Classifier: Programming Language :: Python :: 3.10
Classifier: Programming Language :: Python :: 3.11
License-File: LICENSE.rst
Requires-Dist: httpx[http2]
Requires-Dist: PyJWT (>=2)
Requires-Dist: cryptography (>=40.0.2)
Requires-Dist: pytz
Provides-Extra: dev
Requires-Dist: pytest ; extra == 'dev'
Requires-Dist: black ; extra == 'dev'
Requires-Dist: flake8 ; extra == 'dev'
Requires-Dist: wheel ; extra == 'dev'
